[
  {
    "date": "2026-04-02",
    "equity": 100000.0,
    "spy_equiv": 100000.0
  },
  {
    "date": "2026-04-03",
    "equity": 100000.0,
    "spy_equiv": 100000.0
  },
  {
    "date": "2026-04-07",
    "equity": 100070.74,
    "spy_equiv": 100516.9
  },
  {
    "date": "2026-04-08",
    "equity": 100014.51,
    "spy_equiv": 103077.02
  },
  {
    "date": "2026-04-09",
    "equity": 100887.32,
    "spy_equiv": 103671.68
  },
  {
    "date": "2026-04-10",
    "equity": 101414.66,
    "spy_equiv": 103603.07
  },
  {
    "date": "2026-04-11",
    "equity": 101701.54,
    "spy_equiv": 103603.07
  },
  {
    "date": "2026-04-14",
    "equity": 102171.71,
    "spy_equiv": 105890.25
  },
  {
    "date": "2026-04-15",
    "equity": 102924.59,
    "spy_equiv": 106725.83
  },
  {
    "date": "2026-04-16",
    "equity": 103557.87,
    "spy_equiv": 106988.08
  },
  {
    "date": "2026-04-17",
    "equity": 103906.38,
    "spy_equiv": 108281.11
  },
  {
    "date": "2026-04-18",
    "equity": 104353.13,
    "spy_equiv": 108281.11
  },
  {
    "date": "2026-04-21",
    "equity": 104010.57,
    "spy_equiv": 107357.09
  },
  {
    "date": "2026-04-22",
    "equity": 103879.01,
    "spy_equiv": 108444.26
  },
  {
    "date": "2026-04-23",
    "equity": 104318.31,
    "spy_equiv": 108023.42
  },
  {
    "date": "2026-04-24",
    "equity": 103985.27,
    "spy_equiv": 108860.53
  },
  {
    "date": "2026-04-25",
    "equity": 104289.7,
    "spy_equiv": 108860.53
  },
  {
    "date": "2026-04-28",
    "equity": 104031.63,
    "spy_equiv": 108517.45
  },
  {
    "date": "2026-04-29",
    "equity": 103572.63,
    "spy_equiv": 108500.68
  },
  {
    "date": "2026-04-30",
    "equity": 103780.44,
    "spy_equiv": 109542.1
  },
  {
    "date": "2026-05-01",
    "equity": 104079.31,
    "spy_equiv": 109859.26
  },
  {
    "date": "2026-05-02",
    "equity": 104110.27,
    "spy_equiv": 109859.26
  },
  {
    "date": "2026-05-05",
    "equity": 104110.27,
    "spy_equiv": 110350.24
  },
  {
    "date": "2026-05-06",
    "equity": 103216.62,
    "spy_equiv": 111884.17
  },
  {
    "date": "2026-05-07",
    "equity": 103979.05,
    "spy_equiv": 111542.62
  },
  {
    "date": "2026-05-08",
    "equity": 103095.29,
    "spy_equiv": 112459.02
  },
  {
    "date": "2026-05-09",
    "equity": 103149.57,
    "spy_equiv": 112459.02
  },
  {
    "date": "2026-05-12",
    "equity": 102693.59,
    "spy_equiv": 112558.13
  },
  {
    "date": "2026-05-13",
    "equity": 102738.51,
    "spy_equiv": 113184.82
  },
  {
    "date": "2026-05-14",
    "equity": 101933.97,
    "spy_equiv": 113610.23
  },
  {
    "date": "2026-05-15",
    "equity": 102259.25,
    "spy_equiv": 112696.88
  },
  {
    "date": "2026-05-16",
    "equity": 101345.44,
    "spy_equiv": 112696.88
  }
]
